testing_poetry/__init__.py
testing_poetry/main.py
testing_poetry-1.0.3.dist-info/METADATA
testing_poetry-1.0.3.dist-info/WHEEL
testing_poetry-1.0.3.dist-info/RECORD
