Metadata-Version: 2.1
Name: testing-poetry
Version: 1.0.3
Summary: berikut projek pertama poetry (testing)
Author: Your Name
Author-email: you@example.com
Requires-Python: >=3.10,<4.0
Classifier: Programming Language :: Python :: 3
Classifier: Programming Language :: Python :: 3.10
Classifier: Programming Language :: Python :: 3.11
